psiopenephys/__init__.py
psiopenephys/client.py
psiopenephys/version.py
psiopenephys-0.0.1.dist-info/LICENSE.txt
psiopenephys-0.0.1.dist-info/METADATA
psiopenephys-0.0.1.dist-info/WHEEL
psiopenephys-0.0.1.dist-info/top_level.txt
psiopenephys-0.0.1.dist-info/RECORD
