Metadata-Version: 2.1
Name: psiopenephys
Version: 0.0.1
Summary: Video tools supporting psiexperiment that can also be used as a stand-alone client/server architecture by other programs.
Author-email: Brad Buran <buran@ohsu.edu>
Maintainer-email: Brad Buran <buran@ohsu.edu>
Requires-Python: >=3.7
License-File: LICENSE.txt
Requires-Dist: requests
Provides-Extra: test
Requires-Dist: pytest ; extra == 'test'
